Workbook

Sheet Main
E2: Last checked | F2: Today | G2: Earnings
B3: RHM | C3: Price | D3: 1744.5 | E3: 45906 | F3: =TODAY() -> 45934 | G3: 45967
C4: Shares | D4: 43.84 | E4: Q225
C5: MC | D5: =D3*D4 -> 76478.88
C6: Cash | D6: =1083+328 -> 1411 | E6: Q225
C7: Debt | D7: =193+1511 -> 1704 | E7: Q225
C8: Net Cash | D8: =D6-D7 -> -293
C9: EV | D9: =D5-D8 -> 76771.88

Sheet Model
C2: Q121 | D2: Q221 | E2: Q321 | F2: Q421 | G2: Q122 | H2: Q222 | I2: Q322 | J2: Q422 | K2: Q123 | L2: Q223 | M2: Q323 | N2: Q423 | O2: Q124 | P2: Q224 | Q2: Q324 | R2: Q424 | S2: Q125 | T2: Q225 | U2: Q325 | V2: Q425 | Y2: 2019 | Z2: 2020 | AA2: 2021 | AB2: 2022 | AC2: 2023 | AD2: 2024 | AE2: 2025 | AF2: 2026 | AG2: 2027 | AH2: 2028 | AI2: 2029 | AJ2: 2030 | AK2: 2031 | AL2: 2032 | AM2: 2033 | AN2: 2034 | AO2: 2035
B3: Booked Business | J3: 3521 | K3: 1230 | L3: =1775-K3 -> 545 | M3: 592 | N3: 3480 | O3: 620 | P3: =1357-O3 -> 737 | Q3: =2119-P3-O3 -> 762 | R3: =2508-Q3-P3-O3 -> 389 | S3: 325 | T3: 664 | AB3: 3521 | AC3: 3480 | AD3: 2508
B4: Frame Nomination | J4: 350 | K4: 370 | L4: =1163-K4 -> 793 | M4: 5877 | N4: 7362 | O4: 0 | P4: =7478-O4 -> 7478 | Q4: =10858-P4-O4 -> 3380 | R4: =11518-Q4-P4-O4 -> 660 | S4: 9348 | T4: 433 | AB4: 350 | AC4: 7362 | AD4: 11518
B5: Frame Utilisation | J5: 0 | K5: 0 | L5: =-638-K5 -> -638 | M5: -1726 | N5: -2804 | O5: -444 | P5: =-2369-O5 -> -1925 | Q5: =-2824-P5-O5 -> -455 | R5: =-3738-Q5-P5-O5 -> -914 | S5: -1995 | T5: -256 | AB5: 0 | AC5: -2804 | AD5: -3738
B6: Order Intake | J6: 5629 | K6: 1504 | L6: 3392 | M6: 2570 | N6: 11843 | O6: 3757 | P6: =8910-O6 -> 5153 | Q6: =11275-P6-O6 -> 2365 | R6: =16554-Q6-P6-O6 -> 5279 | S6: 3361 | T6: 1798 | AB6: 5629 | AC6: 11843 | AD6: 16554
B7: Rheinmetall Nomination | J7: =SUM(J3:J6) -> 9500 | K7: =SUM(K3:K6) -> 3104 | L7: =SUM(L3:L6) -> 4092 | M7: =SUM(M3:M6) -> 7313 | N7: =SUM(N3:N6) -> 19881 | O7: =SUM(O3:O6) -> 3933 | P7: =SUM(P3:P6) -> 11443 | Q7: =SUM(Q3:Q6) -> 6052 | ... T7: =SUM(T3:T6) -> 2639 | AB7: =SUM(AB3:AB6) -> 9500 | AC7: =SUM(AC3:AC6) -> 19881 | AD7: =SUM(AD3:AD6) -> 26842
B8: Nominated Backlog | J8: 8056 | K8: 8741 | L8: 8806 | M8: 8875 | N8: 8381 | O8: 8461 | P8: 7938 | Q8: 8060 | R8: 7712 | S8: 6994 | T8: 7192 | AB8: 8056 | AC8: 8381 | AD8: 7712
B9: Frame Backlog | J9: 3427 | K9: 3750 | L9: 3255 | M9: 8118 | N9: 7931 | O9: 7596 | P9: 13041 | Q9: 15896 | R9: 16533 | S9: 22987 | T9: 23707 | AB9: 3427 | AC9: 7931 | AD9: 16533
B10: Order Backlog | J10: 15089 | K10: 15703 | L10: 17989 | M10: 19751 | N10: 21977 | O10: 24140 | P10: 27661 | Q10: 27950 | R10: 30728 | S10: 32579 | T10: 32266 | AB10: 15089 | AC10: 21977 | AD10: 30728
B11: Total Backlog | J11: 26572 | K11: =SUM(K8:K10) -> 28194 | L11: =SUM(L8:L10) -> 30050 | M11: =SUM(M8:M10) -> 36744 | N11: 38290 | O11: =SUM(O8:O10) -> 40197 | P11: =SUM(P8:P10) -> 48640 | Q11: =SUM(Q8:Q10) -> 51906 | R11: =SUM(R8:R10) -> 54973 | S11: =SUM(S8:S10) -> 62560 | T11: =SUM(T8:T10) -> 63165 | AB11: =SUM(AB8:AB10) -> 26572 | AC11: =SUM(AC8:AC10) -> 38289 | AD11: =SUM(AD8:AD10) -> 54973
B13: Vehicle Systems revenue | C13: 406 | D13: 461 | G13: 395 | H13: 446 | I13: 466 | J13: =AB13-I13-H13-G13 -> 944 | K13: 457 | L13: 545 | M13: 653 | N13: =AC13-M13-L13-K13 -> 922 | O13: 489 | P13: 805 | Q13: 1234 | R13: =AD13-Q13-P13-O13 -> 1241 | S13: 945 | T13: 930 | U13: =Q13*1.2 -> 1480.8 | V13: =R13*1.35 -> 1675.35 | Z13: 1828 | AA13: 1875 | AB13: 2251 | AC13: 2577 | AD13: 3769 | AE13: =SUM(S13:V13) -> 5031.15 | AF13: =AE13*1.22 -> 6138.003 | AG13: =AF13*1.08 -> 6629.0432 | AH13: =AG13*1.05 -> 6960.4954 | AI13: =AH13*1.03 -> 7169.3103 | AJ13: =AI13*1.02 -> 7312.6965 | AK13: =AJ13*1.02 -> 7458.9504 | AL13: =AK13*1.02 -> 7608.1294 | AM13: =AL13*1.02 -> 7760.292 | AN13: =AM13*1.02 -> 7915.4978 | AO13: =AN13*1.02 -> 8073.8078
B14: Weapon and Ammunition revenue | C14: 210 | D14: 231 | G14: 216 | H14: 257 | I14: 228 | J14: =AB14-I14-H14-G14 -> 437 | K14: 174 | L14: 248 | M14: 379 | N14: =AC14-M14-L14-K14 -> 680 | O14: 321 | P14: 635 | Q14: 447 | R14: =AD14-Q14-P14-O14 -> 1132 | S14: 530 | T14: 661 | U14: =Q14*1.8 -> 804.6 | V14: =R14*1.2 -> 1358.4 | Z14: 1118 | AA14: 1139 | AB14: 1138 | AC14: 1481 | AD14: 2535 | AE14: =SUM(S14:V14) -> 3354 | AF14: =AE14*1.2 -> 4024.8 | AG14: =AF14*1.1 -> 4427.28 | AH14: =AG14*1.05 -> 4648.644 | AI14: =AH14*1.03 -> 4788.1033 | AJ14: =AI14*1.02 -> 4883.8654 | AK14: =AJ14*1.02 -> 4981.5427 | AL14: =AK14*1.02 -> 5081.1735 | AM14: =AL14*1.02 -> 5182.797 | AN14: =AM14*1.02 -> 5286.453 | AO14: =AN14*1.02 -> 5392.182
B15: Electronic Solutions revenue | C15: 141 | D15: 162 | G15: 132 | H15: 190 | I15: 186 | J15: =AB15-I15-H15-G15 -> 433 | K15: 185 | L15: 211 | M15: 204 | N15: =AC15-M15-L15-K15 -> 418 | O15: 227 | P15: 272 | Q15: 284 | R15: =AD15-Q15-P15-O15 -> 533 | S15: 335 | T15: 403 | U15: =Q15*1.4 -> 397.6 | V15: =R15*1.33 -> 708.89 | Z15: 776 | AA15: 745 | AB15: 941 | AC15: 1018 | AD15: 1316 | AE15: =SUM(S15:V15) -> 1844.49 | AF15: =AE15*1.22 -> 2250.2778 | AG15: =AF15*1.15 -> 2587.8195 | AH15: =AG15*1.08 -> 2794.845 | AI15: =AH15*1.05 -> 2934.5873 | AJ15: =AI15*1.04 -> 3051.9708 | AK15: =AJ15*1.03 -> 3143.5299 | AL15: =AK15*1.03 -> 3237.8358 | AM15: =AL15*1.03 -> 3334.9709 | AN15: =AM15*1.03 -> 3435.02 | AO15: =AN15*1.03 -> 3538.0706
B16: Power Systems revenue | C16: =351+158 -> 509 | D16: =307+159 -> 466 | G16: =326+190 -> 516 | H16: =325+183 -> 508 | I16: =339+187 -> 526 | J16: =AB16-I16-H16-G16 -> 502 | K16: 541 | L16: 484 | M16: =327+197 -> 524 | N16: =AC16-M16-L16-K16 -> 532 | O16: 540 | P16: 513 | Q16: 484 | R16: =AD16-Q16-P16-O16 -> 495 | S16: 504 | T16: 480 | U16: =Q16*0.95 -> 459.8 | V16: =R16*0.98 -> 485.1 | Z16: =1147+533 -> 1680 | AA16: =1229+647 -> 1876 | AB16: =1313+739 -> 2052 | AC16: =1346+735 -> 2081 | AD16: 2032 | AE16: =SUM(S16:V16) -> 1928.9 | AF16: =AE16*1.01 -> 1948.189 | AG16: =AF16*1.01 -> 1967.6709 | AH16: =AG16*1.01 -> 1987.3476 | AI16: =AH16*1.01 -> 2007.2211 | AJ16: =AI16*1.01 -> 2027.2933 | AK16: =AJ16*1.01 -> 2047.5662 | AL16: =AK16*1.01 -> 2068.0419 | AM16: =AL16*1.01 -> 2088.7223 | ... AO16: =AN16*1.01 -> 2130.7056
B17: Other revenue | C17: 2 | D17: -4 | G17: 7 | H17: 7 | I17: 9 | J17: =AB17-I17-H17-G17 -> 5 | K17: 6 | L17: 9 | M17: -2 | N17: =AC17-M17-L17-K17 -> 5 | O17: 5 | P17: 10 | Q17: 4 | R17: =AD17-Q17-P17-O17 -> 80 | S17: -9 | T17: -43 | U17: =Q17*1.35 -> 5.4 | V17: =R17*1.5 -> 120 | Z17: 3 | AA17: 24 | AB17: 28 | AC17: 18 | AD17: 99 | AE17: =SUM(S17:V17) -> 73.4 | AF17: =AE17*1.4 -> 102.76 | AG17: =AF17*1.3 -> 133.588 | AH17: =AG17*1.2 -> 160.3056 | AI17: =AH17*1.1 -> 176.33616 | AJ17: =AI17*1.05 -> 185.15297 | AK17: =AJ17*1.05 -> 194.41062 | AL17: =AK17*1.05 -> 204.13115 | AM17: =AL17*1.05 -> 214.3377 | AN17: =AM17*1.05 -> 225.05459 | AO17: =AN17*1.05 -> 236.30732
B18: Revenue | C18: 1268 | D18: =SUM(D13:D17) -> 1316 | G18: 1266 | H18: =SUM(H13:H17) -> 1408 | I18: 1415 | J18: =SUM(J13:J17) -> 2321 | K18: =SUM(K13:K17) -> 1363 | L18: =SUM(L13:L17) -> 1497 | M18: 1758 | N18: =SUM(N13:N17) -> 2557 | O18: =SUM(O13:O17) -> 1582 | P18: =SUM(P13:P17) -> 2235 | Q18: =SUM(Q13:Q17) -> 2453 | R18: =SUM(R13:R17) -> 3481 | S18: =SUM(S13:S17) -> 2305 | T18: =SUM(T13:T17) -> 2431 | U18: =SUM(U13:U17) -> 3148.2 | V18: =SUM(V13:V17) -> 4347.74 | Z18: =SUM(Z13:Z17) -> 5405 | AA18: =SUM(AA13:AA17) -> 5659 | AB18: =SUM(AB13:AB17) -> 6410 | AC18: =SUM(AC13:AC17) -> 7175 | AD18: 9751 | AE18: =SUM(AE13:AE17) -> 12231.94 | AF18: =SUM(AF13:AF17) -> 14464.03 | AG18: =SUM(AG13:AG17) -> 15745.402 | AH18: =SUM(AH13:AH17) -> 16551.638 | AI18: =SUM(AI13:AI17) -> 17075.558 | AJ18: =SUM(AJ13:AJ17) -> 17460.979 | AK18: =SUM(AK13:AK17) -> 17826 | AL18: =SUM(AL13:AL17) -> 18199.312 | ... AO18: =SUM(AO13:AO17) -> 19371.073
B19: Inventory cost | C19: -85 | D19: -29 | G19: -142 | H19: -86 | I19: -138 | J19: =AB19-I19-H19-G19 -> 213 | K19: -332 | L19: -213 | M19: -173 | N19: =AC19-M19-L19-K19 -> 22 | O19: -432 | P19: -1 | Q19: 130 | R19: =AD19-Q19-P19-O19 -> 136 | S19: -247 | T19: -353 | U19: 0 | V19: 0 | Z19: -142 | AA19: -117 | AB19: -153 | AC19: -696 | AD19: -167 | AF19: =AE19*0.97 -> 0 | AG19: =AF19*0.97 -> 0 | AH19: =AG19*0.97 -> 0 | AI19: =AH19*0.97 -> 0 | AJ19: =AI19*0.97 -> 0 | AK19: =AJ19*0.97 -> 0 | AL19: =AK19*0.97 -> 0 | AM19: =AL19*0.97 -> 0 | ... AO19: =AN19*0.97 -> 0
B20: Cost of materials | C20: 665 | D20: 635 | G20: 684 | H20: 714 | I20: 797 | J20: =AB20-I20-H20-G20 -> 988 | K20: 893 | L20: 861 | M20: 1007 | N20: =AC20-M20-L20-K20 -> 1174 | O20: 1039 | P20: 1087 | Q20: 1170 | R20: =AD20-Q20-P20-O20 -> 1563 | S20: 1314 | T20: 1485 | Z20: 2792 | AA20: 2745 | AB20: 3183 | AC20: 3935 | AD20: 4859 | AF20: =AF18*0.5 -> 7232.0149 | AG20: =AG18*0.5 -> 7872.7008 | AH20: =AH18*0.5 -> 8275.8188 | AI20: =AI18*0.5 -> 8537.779 | AJ20: =AJ18*0.5 -> 8730.4894 | AK20: =AK18*0.5 -> 8912.9999 | AL20: =AL18*0.5 -> 9099.6559 | AM20: =AM18*0.5 -> 9290.5599 | ... AO20: =AO18*0.5 -> 9685.5367
B21: Personnel costs | C21: 414 | D21: 423 | G21: 457 | H21: 464 | I21: 440 | J21: =AB21-I21-H21-G21 -> 475 | K21: 500 | L21: 507 | M21: 495 | N21: =AC21-M21-L21-K21 -> 545 | O21: 581 | P21: 578 | Q21: 572 | R21: =AD21-Q21-P21-O21 -> 642 | S21: 696 | T21: 704 | Z21: 1537 | AA21: 1643 | AB21: 1836 | AC21: 2047 | AD21: 2373 | AF21: =AF18*0.25 -> 3616.0075 | AG21: =AG18*0.25 -> 3936.3504 | AH21: =AH18*0.25 -> 4137.9094 | AI21: =AI18*0.25 -> 4268.8895 | AJ21: =AJ18*0.25 -> 4365.2447 | AK21: =AK18*0.25 -> 4456.5 | AL21: =AL18*0.25 -> 4549.8279 | AM21: =AM18*0.25 -> 4645.28 | ... AO21: =AO18*0.25 -> 4842.7683
B22: Total cost of sales | C22: =SUM(C19:C21) -> 994 | D22: =SUM(D19:D21) -> 1029 | G22: =SUM(G19:G21) -> 999 | H22: =SUM(H19:H21) -> 1092 | I22: =SUM(I19:I21) -> 1099 | J22: =SUM(J19:J21) -> 1676 | K22: =SUM(K19:K21) -> 1061 | L22: =SUM(L19:L21) -> 1155 | M22: =SUM(M19:M21) -> 1329 | N22: =SUM(N19:N21) -> 1741 | ... T22: =SUM(T19:T21) -> 1836 | U22: =U18-U23 -> 2329.668 | V22: =V18-V23 -> 2869.5084 | Z22: =SUM(Z19:Z21) -> 4187 | AA22: =SUM(AA19:AA21) -> 4271 | AB22: =SUM(AB19:AB21) -> 4866 | AC22: =SUM(AC19:AC21) -> 5286 | AD22: =SUM(AD19:AD21) -> 7065 | AE22: =SUM(S22:V22) -> 8798.1764 | AF22: =SUM(AF19:AF21) -> 10848.022 | AG22: =SUM(AG19:AG21) -> 11809.051 | AH22: =SUM(AH19:AH21) -> 12413.728 | AI22: =SUM(AI19:AI21) -> 12806.669 | AJ22: =SUM(AJ19:AJ21) -> 13095.734 | AK22: =SUM(AK19:AK21) -> 13369.5 | AL22: =SUM(AL19:AL21) -> 13649.484 | AM22: =SUM(AM19:AM21) -> 13935.84 | ... AO22: =SUM(AO19:AO21) -> 14528.305
B23: Gross profit | C23: =C18-C22 -> 274 | D23: =D18-D22 -> 287 | G23: =G18-G22 -> 267 | H23: =H18-H22 -> 316 | I23: =I18-I22 -> 316 | J23: =J18-J22 -> 645 | K23: =K18-K22 -> 302 | L23: =L18-L22 -> 342 | M23: =M18-M22 -> 429 | N23: =N18-N22 -> 816 | ... T23: =T18-T22 -> 595 | U23: =U18*0.26 -> 818.532 | V23: =V18*0.34 -> 1478.2316 | Z23: =Z18-Z22 -> 1218 | AA23: =AA18-AA22 -> 1388 | AB23: =AB18-AB22 -> 1544 | AC23: =AC18-AC22 -> 1889 | AD23: =AD18-AD22 -> 2686 | AE23: =AE18-AE22 -> 3433.7636 | AF23: =AF18-AF22 -> 3616.0075 | AG23: =AG18-AG22 -> 3936.3504 | ... AO23: =AO18-AO22 -> 4842.7683
B24: D&A | C24: 58 | D24: 58 | G24: 60 | H24: 62 | I24: 63 | J24: =AB24-I24-H24-G24 -> 64 | K24: 63 | L24: 63 | M24: 79 | N24: =AC24-M24-L24-K24 -> 103 | O24: 91 | P24: 91 | Q24: 95 | R24: =AD24-Q24-P24-O24 -> 126 | S24: 112 | T24: 127 | U24: 95 | V24: 130 | Z24: 282 | AA24: 251 | AB24: 249 | AC24: 308 | AD24: 403
B25: Other operating income | C25: -21 | D25: -30 | G25: -29 | H25: -39 | I25: -53 | J25: =AB25-I25-H25-G25 -> -100 | K25: -32 | L25: -22 | M25: -41 | N25: =AC25-M25-L25-K25 -> -58 | O25: -42 | P25: -39 | Q25: -51 | R25: =AD25-Q25-P25-O25 -> -96 | S25: -36 | T25: -51 | U25: =Q25*1.3 -> -66.3 | V25: =R25*1.3 -> -124.8 | Z25: -114 | AA25: -134 | AB25: -221 | AC25: -153 | AD25: -228
B26: Other operating expenses | C26: 149 | D26: 154 | G26: 153 | H26: 166 | I26: 194 | J26: =AB26-I26-H26-G26 -> 255 | K26: 182 | L26: 183 | M26: 219 | N26: =AC26-M26-L26-K26 -> 305 | O26: 228 | P26: 277 | Q26: 247 | R26: =AD26-Q26-P26-O26 -> 368 | S26: 287 | T26: 287 | U26: =Q26*1.15 -> 284.05 | V26: =R26*1.1 -> 404.8 | Z26: 642 | AA26: 656 | AB26: 768 | AC26: 889 | AD26: 1120
B27: Total operating expenses | C27: =SUM(C24:C26) -> 186 | D27: =SUM(D24:D26) -> 182 | G27: =SUM(G24:G26) -> 184 | H27: =SUM(H24:H26) -> 189 | I27: =SUM(I24:I26) -> 204 | J27: =SUM(J24:J26) -> 219 | K27: =SUM(K24:K26) -> 213 | L27: =SUM(L24:L26) -> 224 | M27: =SUM(M24:M26) -> 257 | N27: =SUM(N24:N26) -> 350 | ... V27: =SUM(V24:V26) -> 410 | Z27: =SUM(Z24:Z26) -> 810 | AA27: =SUM(AA24:AA26) -> 773 | AB27: =SUM(AB24:AB26) -> 796 | AC27: =SUM(AC24:AC26) -> 1044 | AD27: =SUM(AD24:AD26) -> 1295 | AE27: =SUM(S27:V27) -> 1448.75 | AF27: =(AE27*1.05) -> 1521.1875 | AG27: =AF27*1.04 -> 1582.035 | AH27: =AG27*1.03 -> 1629.4961 | AI27: =AH27*1.02 -> 1662.086 | AJ27: =AI27*1.02 -> 1695.3277 | AK27: =AJ27*1.02 -> 1729.2342 | AL27: =AK27*1.02 -> 1763.8189 | AM27: =AL27*1.02 -> 1799.0953 | AN27: =AM27*1.02 -> 1835.0772 | AO27: =AN27*1.02 -> 1871.7788
B28: Operating profit | C28: =C23-C27 -> 88 | D28: =D23-D27 -> 105 | G28: =G23-G27 -> 83 | H28: =H23-H27 -> 127 | I28: =I23-I27 -> 112 | J28: =J23-J27 -> 426 | K28: =K23-K27 -> 89 | L28: =L23-L27 -> 118 | M28: =M23-M27 -> 172 | N28: =N23-N27 -> 466 | ... V28: =V23-V27 -> 1068.2316 | Z28: =Z23-Z27 -> 408 | AA28: =AA23-AA27 -> 615 | AB28: =AB23-AB27 -> 748 | AC28: =AC23-AC27 -> 845 | AD28: =AD23-AD27 -> 1391 | AE28: =AE23-AE27 -> 1985.0136 | AF28: =AF23-AF27 -> 2094.82 | AG28: =AG23-AG27 -> 2354.3154 | ... AO28: =AO23-AO27 -> 2970.9896
B29: Investments | C29: -7 | D29: -4 | G29: -17 | H29: 2 | I29: -8 | J29: =AB29-I29-H29-G29 -> -16 | K29: 10 | L29: 2 | M29: -6 | N29: =AC29-M29-L29-K29 -> -63 | O29: 1 | P29: 4 | Q29: 12 | R29: =AD29-Q29-P29-O29 -> 20 | S29: 3 | T29: 0 | Z29: -13 | AA29: -11 | AB29: -39 | AC29: -57 | AD29: 37
B30: Other financial income | C30: 10 | D30: 1 | G30: 20 | H30: 21 | I30: 3 | J30: =AB30-I30-H30-G30 -> 4 | K30: 2 | L30: -3 | M30: 8 | N30: =AC30-M30-L30-K30 -> -1 | O30: 9 | P30: 2 | Q30: 8 | R30: =AD30-Q30-P30-O30 -> -9 | S30: 3 | T30: -7 | Z30: 24 | AA30: 17 | AB30: 48 | AC30: 6 | AD30: 10
B31: Interest income | C31: -2 | D31: -2 | G31: -1 | H31: -1 | I31: -1 | J31: =AB31-I31-H31-G31 -> -9 | K31: -16 | L31: -3 | M31: -5 | N31: =AC31-M31-L31-K31 -> -5 | O31: -5 | P31: -4 | Q31: -5 | R31: =AD31-Q31-P31-O31 -> -5 | S31: -6 | T31: -4 | Z31: -9 | AA31: -4 | AB31: -12 | AC31: -29 | AD31: -19
B32: Interest expense | C32: 11 | D32: 7 | G32: 8 | H32: 7 | I32: 7 | J32: =AB32-I32-H32-G32 -> 10 | K32: 24 | L32: 18 | M32: 30 | N32: =AC32-M32-L32-K32 -> 39 | O32: 26 | P32: 32 | Q32: 28 | R32: =AD32-Q32-P32-O32 -> 49 | S32: 33 | T32: 20 | Z32: 40 | AA32: 31 | AB32: 32 | AC32: 111 | AD32: 135
B33: Net financial expense | C33: =SUM(C29:C32) -> 12 | D33: =SUM(D29:D32) -> 2 | G33: =SUM(G29:G32) -> 10 | H33: =SUM(H29:H32) -> 29 | I33: =SUM(I29:I32) -> 1 | J33: =SUM(J29:J32) -> -11 | K33: =SUM(K29:K32) -> 20 | L33: =SUM(L29:L32) -> 14 | M33: =SUM(M29:M32) -> 27 | N33: =SUM(N29:N32) -> -30 | ... T33: =SUM(T29:T32) -> 9 | U33: =Q33*1.05 -> 45.15 | V33: =R33*1.05 -> 57.75 | Z33: =SUM(Z29:Z32) -> 42 | AA33: =SUM(AA29:AA32) -> 33 | AB33: =SUM(AB29:AB32) -> 29 | AC33: =SUM(AC29:AC32) -> 31 | AD33: =SUM(AD29:AD32) -> 163 | AE33: =SUM(S33:V33) -> 144.9 | AF33: =AE33*1.03 -> 149.247 | AG33: =AF33*1.03 -> 153.72441 | AH33: =AG33*1.03 -> 158.33614 | AI33: =AH33*1.03 -> 163.08623 | AJ33: =AI33*1.03 -> 167.97881 | AK33: =AJ33*1.03 -> 173.01818 | AL33: =AK33*1.03 -> 178.20872 | AM33: =AL33*1.03 -> 183.55498 | ... AO33: =AN33*1.03 -> 194.73348
B34: Pretax profit | C34: =C28-C33 -> 76 | D34: =D28-D33 -> 103 | G34: =G28-G33 -> 73 | H34: =H28-H33 -> 98 | I34: =I28-I33 -> 111 | J34: =J28-J33 -> 437 | K34: =K28-K33 -> 69 | L34: =L28-L33 -> 104 | M34: =M28-M33 -> 145 | N34: =N28-N33 -> 496 | ... V34: =V28-V33 -> 1010.4816 | Z34: =Z28-Z33 -> 366 | AA34: =AA28-AA33 -> 582 | AB34: =AB28-AB33 -> 719 | AC34: =AC28-AC33 -> 814 | AD34: =AD28-AD33 -> 1228 | AE34: =AE28-AE33 -> 1840.1136 | AF34: =AF28-AF33 -> 1945.573 | AG34: =AG28-AG33 -> 2200.591 | ... AO34: =AO28-AO33 -> 2776.2561
B35: Taxes | C35: 21 | D35: 24 | G35: 15 | H35: 30 | I35: 30 | J35: =AB35-I35-H35-G35 -> 108 | K35: 20 | L35: 31 | M35: 36 | N35: =AC35-M35-L35-K35 -> 98 | O35: 31 | P35: 56 | Q35: 74 | R35: =AD35-Q35-P35-O35 -> 172 | S35: 39 | T35: 53 | U35: =U34*0.27 -> 124.37064 | V35: =V34*0.27 -> 272.83003 | Z35: 83 | AA35: 150 | AB35: 183 | AC35: 185 | AD35: 333 | AE35: =SUM(S35:V35) -> 489.20067 | AF35: =AF34*0.25 -> 486.39324 | AG35: =AG34*0.25 -> 550.14775 | AH35: =AH34*0.25 -> 587.5193 | AI35: =AI34*0.25 -> 610.92933 | AJ35: =AJ34*0.25 -> 625.48455 | AK35: =AK34*0.25 -> 638.56188 | AL35: =AL34*0.25 -> 651.95007 | AM35: =AM34*0.25 -> 665.65742 | ... AO35: =AO34*0.25 -> 694.06402
B36: MI | C36: =-4+9 -> 5 | D36: =103+13 -> 116 | G36: =-1+13 -> 12 | H36: =-5+16 -> 11 | I36: =-5+10 -> 5 | J36: =AB36-I36-H36-G36 -> 32 | K36: =4-3 -> 1 | L36: =17-1 -> 16 | M36: =-2+9 -> 7 | N36: =AC36-M36-L36-K36 -> 71 | O36: =-1+6 -> 5 | P36: =17+72 -> 89 | Q36: 38 | R36: =AD36-Q36-P36-O36 -> 46 | S36: 24 | T36: 27 | U36: =U34*0.1 -> 46.0632 | V36: =V34*0.1 -> 101.04816 | Z36: =283+27 -> 310 | AA36: =100+41 -> 141 | AB36: =-6+66 -> 60 | AC36: =44+51 -> 95 | AD36: =87+91 -> 178 | AE36: =SUM(S36:V36) -> 198.11136 | AF36: =AF34*0.1 -> 194.5573 | AG36: =AG34*0.1 -> 220.0591 | AH36: =AH34*0.1 -> 235.00772 | AI36: =AI34*0.1 -> 244.37173 | AJ36: =AJ34*0.1 -> 250.19382 | AK36: =AK34*0.1 -> 255.42475 | AL36: =AL34*0.1 -> 260.78003 | AM36: =AM34*0.1 -> 266.26297 | ... AO36: =AO34*0.1 -> 277.62561
B37: Net profit | C37: =C34-C35-C36 -> 50 | D37: =D34-D35-D36 -> -37 | G37: =G34-G35-G36 -> 46 | H37: =H34-H35-H36 -> 57 | I37: =I34-I35-I36 -> 76 | J37: =J34-J35-J36 -> 297 | K37: =K34-K35-K36 -> 48 | L37: =L34-L35-L36 -> 57 | M37: =M34-M35-M36 -> 102 | N37: =N34-N35-N36 -> 327 | ... V37: =V34-V35-V36 -> 636.60341 | Z37: =Z34-Z35-Z36 -> -27 | AA37: =AA34-AA35-AA36 -> 291 | AB37: =AB34-AB35-AB36 -> 476 | AC37: =AC34-AC35-AC36 -> 534 | AD37: =AD34-AD35-AD36 -> 717 | AE37: =AE34-AE35-AE36 -> 1152.8016 | AF37: =AF34-AF35-AF36 -> 1264.6224 | AG37: =AG34-AG35-AG36 -> 1430.3841 | ... AO37: =AO34-AO35-AO36 -> 1804.5665 | AP37: =AO37*(1+$AS$45) -> 1786.5208 | AQ37: =AP37*(1+$AS$45) -> 1768.6556 | AR37: =AQ37*(1+$AS$45) -> 1750.969 | AS37: =AR37*(1+$AS$45) -> 1733.4593 | AT37: =AS37*(1+$AS$45) -> 1716.1247 | AU37: =AT37*(1+$AS$45) -> 1698.9635 | AV37: =AU37*(1+$AS$45) -> 1681.9739 | AW37: =AV37*(1+$AS$45) -> 1665.1541 | ... EV37: =EU37*(1+$AS$45) -> 591.3975
B38: Shares | C38: 43.43 | D38: 43.43 | G38: 43.43 | H38: 43.43 | I38: 43.43 | J38: 43.43 | K38: 43.43 | L38: 43.43 | M38: 43.43 | N38: 43.43 | O38: 43.43 | P38: 43.43 | Q38: 43.43 | R38: 43.43 | S38: 43.84 | T38: 43.84 | U38: 43.84 | V38: 43.84 | Z38: 43.43 | AA38: 43.43 | AB38: 43.43 | AC38: 43.43 | AD38: 43.43 | AE38: 43.84 | AF38: 43.84 | AG38: 43.84 | AH38: 43.84 | AI38: 43.84 | AJ38: 43.84 | AK38: 43.84 | AL38: 43.84 | AM38: 43.84 | AN38: 43.84 | AO38: 43.84
B39: EPS | C39: =C37/C38 -> 1.1512779 | D39: =D37/D38 -> -0.85194566 | G39: =G37/G38 -> 1.0591757 | H39: =H37/H38 -> 1.3124568 | I39: =I37/I38 -> 1.7499424 | J39: =J37/J38 -> 6.8385908 | K39: =K37/K38 -> 1.1052268 | L39: =L37/L38 -> 1.3124568 | M39: =M37/M38 -> 2.348607 | N39: =N37/N38 -> 7.5293576 | ... V39: =V37/V38 -> 14.521063 | Z39: =Z37/Z38 -> -0.62169008 | AA39: =AA37/AA38 -> 6.7004375 | AB39: =AB37/AB38 -> 10.960166 | AC39: =AC37/AC38 -> 12.295648 | AD39: =AD37/AD38 -> 16.509325 | AE39: =AE37/AE38 -> 26.295656 | AF39: =AF37/AF38 -> 28.846314 | AG39: =AG37/AG38 -> 32.627376 | ... AO39: =AO37/AO38 -> 41.162556
B41: Order Backlog y/y | O41: =O10/K10-1 -> 0.53728587 | P41: =P10/L10-1 -> 0.5376619 | Q41: =Q10/M10-1 -> 0.41511822 | R41: =R10/N10-1 -> 0.39818902 | S41: =S10/O10-1 -> 0.34958575 | T41: =T10/P10-1 -> 0.16647988 | AC41: =AC10/AB10-1 -> 0.45649148 | AD41: =AD10/AC10-1 -> 0.39818902
B42: Backlog y/y | N42: =N11/J11-1 -> 0.44099052 | O42: =O11/K11-1 -> 0.42572888 | P42: =P11/L11-1 -> 0.61863561 | Q42: =Q11/M11-1 -> 0.4126388 | R42: =R11/N11-1 -> 0.43570123 | S42: =S11/O11-1 -> 0.55633505 | T42: =T11/P11-1 -> 0.29862253 | AC42: =AC11/AB11-1 -> 0.44095288 | AD42: =AD11/AC11-1 -> 0.43573872
B44: Vehicle Systems revenue y/y | G44: =G13/C13-1 -> -0.027093596 | H44: =H13/D13-1 -> -0.032537961 | K44: =K13/G13-1 -> 0.15696203 | L44: =L13/H13-1 -> 0.22197309 | M44: =M13/I13-1 -> 0.40128755 | N44: =N13/J13-1 -> -0.023305085 | O44: =O13/K13-1 -> 0.070021882 | P44: =P13/L13-1 -> 0.47706422 | Q44: =Q13/M13-1 -> 0.88973966 | R44: =R13/N13-1 -> 0.34598698 | ... V44: =V13/R13-1 -> 0.35 | AA44: =AA13/Z13-1 -> 0.02571116 | AB44: =AB13/AA13-1 -> 0.20053333 | AC44: =AC13/AB13-1 -> 0.14482452 | AD44: =AD13/AC13-1 -> 0.46255336 | AE44: =AE13/AD13-1 -> 0.33487663 | AF44: =AF13/AE13-1 -> 0.22 | AG44: =AG13/AF13-1 -> 0.08 | AH44: =AH13/AG13-1 -> 0.05 | ... AO44: =AO13/AN13-1 -> 0.02
B45: Weapon and Ammunition revenue y/y | G45: =G14/C14-1 -> 0.028571429 | H45: =H14/D14-1 -> 0.11255411 | K45: =K14/G14-1 -> -0.19444444 | L45: =L14/H14-1 -> -0.035019455 | M45: =M14/I14-1 -> 0.6622807 | N45: =N14/J14-1 -> 0.55606407 | O45: =O14/K14-1 -> 0.84482759 | P45: =P14/L14-1 -> 1.5604839 | Q45: =Q14/M14-1 -> 0.17941953 | R45: =R14/N14-1 -> 0.66470588 | ... V45: =V14/R14-1 -> 0.2 | AA45: =AA14/Z14-1 -> 0.018783542 | AB45: =AB14/AA14-1 -> -0.00087796313 | AC45: =AC14/AB14-1 -> 0.30140598 | AD45: =AD14/AC14-1 -> 0.7116813 | AE45: =AE14/AD14-1 -> 0.32307692 | AF45: =AF14/AE14-1 -> 0.2 | AG45: =AG14/AF14-1 -> 0.1 | AH45: =AH14/AG14-1 -> 0.05 | ... AO45: =AO14/AN14-1 -> 0.02 | AR45: Maturity | AS45: -0.01
B46: Electronic Solutions revenue y/y | G46: =G15/C15-1 -> -0.063829787 | H46: =H15/D15-1 -> 0.17283951 | K46: =K15/G15-1 -> 0.40151515 | L46: =L15/H15-1 -> 0.11052632 | M46: =M15/I15-1 -> 0.096774194 | N46: =N15/J15-1 -> -0.034642032 | O46: =O15/K15-1 -> 0.22702703 | P46: =P15/L15-1 -> 0.28909953 | Q46: =Q15/M15-1 -> 0.39215686 | R46: =R15/N15-1 -> 0.27511962 | ... V46: =V15/R15-1 -> 0.33 | AA46: =AA15/Z15-1 -> -0.039948454 | AB46: =AB15/AA15-1 -> 0.26308725 | AC46: =AC15/AB15-1 -> 0.081827843 | AD46: =AD15/AC15-1 -> 0.29273084 | AE46: =AE15/AD15-1 -> 0.40158815 | AF46: =AF15/AE15-1 -> 0.22 | AG46: =AG15/AF15-1 -> 0.15 | AH46: =AH15/AG15-1 -> 0.08 | ... AO46: =AO15/AN15-1 -> 0.03 | AR46: Discount rate | AS46: 0.07
B47: Power Systems revenue y/y | G47: =G16/C16-1 -> 0.013752456 | H47: =H16/D16-1 -> 0.090128755 | K47: =K16/G16-1 -> 0.048449612 | L47: =L16/H16-1 -> -0.047244094 | M47: =M16/I16-1 -> -0.0038022814 | N47: =N16/J16-1 -> 0.059760956 | O47: =O16/K16-1 -> -0.0018484288 | P47: =P16/L16-1 -> 0.059917355 | Q47: =Q16/M16-1 -> -0.076335878 | R47: =R16/N16-1 -> -0.069548872 | ... V47: =V16/R16-1 -> -0.02 | AA47: =AA16/Z16-1 -> 0.11666667 | AB47: =AB16/AA16-1 -> 0.093816631 | AC47: =AC16/AB16-1 -> 0.014132554 | AD47: =AD16/AC16-1 -> -0.023546372 | AE47: =AE16/AD16-1 -> -0.050738189 | AF47: =AF16/AE16-1 -> 0.01 | AG47: =AG16/AF16-1 -> 0.01 | AH47: =AH16/AG16-1 -> 0.01 | ... AO47: =AO16/AN16-1 -> 0.01 | AR47: NPV | AS47: =NPV(AS46,AE37:EV37) -> 22056.291
B48: Other revenue y/y | G48: =G17/C17-1 -> 2.5 | H48: =H17/D17-1 -> -2.75 | K48: =K17/G17-1 -> -0.14285714 | L48: =L17/H17-1 -> 0.28571429 | M48: =M17/I17-1 -> -1.2222222 | N48: =N17/J17-1 -> 0 | O48: =O17/K17-1 -> -0.16666667 | P48: =P17/L17-1 -> 0.11111111 | Q48: =Q17/M17-1 -> -3 | R48: =R17/N17-1 -> 15 | ... V48: =V17/R17-1 -> 0.5 | AA48: =AA17/Z17-1 -> 7 | AB48: =AB17/AA17-1 -> 0.16666667 | AC48: =AC17/AB17-1 -> -0.35714286 | AD48: =AD17/AC17-1 -> 4.5 | AE48: =AE17/AD17-1 -> -0.25858586 | AF48: =AF17/AE17-1 -> 0.4 | AG48: =AG17/AF17-1 -> 0.3 | AH48: =AH17/AG17-1 -> 0.2 | ... AO48: =AO17/AN17-1 -> 0.05 | AR48: Net cash | AS48: =Main!D8 -> -293
B49: Revenue y/y | G49: =G18/C18-1 -> -0.0015772871 | H49: =H18/D18-1 -> 0.069908815 | K49: =K18/G18-1 -> 0.076619273 | L49: =L18/H18-1 -> 0.063210227 | M49: =M18/I18-1 -> 0.24240283 | N49: =N18/J18-1 -> 0.10168031 | O49: =O18/K18-1 -> 0.16067498 | P49: =P18/L18-1 -> 0.49298597 | Q49: =Q18/M18-1 -> 0.39533561 | R49: =R18/N18-1 -> 0.36136097 | ... V49: =V18/R18-1 -> 0.24899167 | AA49: =AA18/Z18-1 -> 0.046993525 | AB49: =AB18/AA18-1 -> 0.13270896 | AC49: =AC18/AB18-1 -> 0.11934477 | AD49: =AD18/AC18-1 -> 0.35902439 | AE49: =AE18/AD18-1 -> 0.25442929 | AF49: =AF18/AE18-1 -> 0.18248044 | AG49: =AG18/AF18-1 -> 0.088590235 | AH49: =AH18/AG18-1 -> 0.051204539 | ... AO49: =AO18/AN18-1 -> 0.021054508 | AR49: Value | AS49: =AS47+AS48 -> 21763.291
B50: Operating revenue y/y | G50: =(G18+G19)/(C18+C19)-1 -> -0.049873204 | H50: =(H18+H19)/(D18+D19)-1 -> 0.027195027 | K50: =(K18+K19)/(G18+G19)-1 -> -0.082740214 | L50: =(L18+L19)/(H18+H19)-1 -> -0.028744327 | M50: =(M18+M19)/(I18+I19)-1 -> 0.24119029 | N50: =(N18+N19)/(J18+J19)-1 -> 0.017758485 | O50: =(O18+O19)/(K18+K19)-1 -> 0.11542192 | P50: =(P18+P19)/(L18+L19)-1 -> 0.73987539 | Q50: =(Q18+Q19)/(M18+M19)-1 -> 0.629653 | R50: =(R18+R19)/(N18+N19)-1 -> 0.40248158 | ... V50: =(V18+V19)/(R18+R19)-1 -> 0.20202931 | AA50: =(AA18+AA19)/(Z18+Z19)-1 -> 0.05301159 | AB50: =(AB18+AB19)/(AA18+AA19)-1 -> 0.1290148 | AC50: =(AC18+AC19)/(AB18+AB19)-1 -> 0.035480262 | AD50: =(AD18+AD19)/(AC18+AC19)-1 -> 0.47924062 | AE50: =(AE18+AE19)/(AD18+AD19)-1 -> 0.27628756 | AF50: =(AF18+AF19)/(AE18+AE19)-1 -> 0.18248044 | AG50: =(AG18+AG19)/(AF18+AF19)-1 -> 0.088590235 | AH50: =(AH18+AH19)/(AG18+AG19)-1 -> 0.051204539 | ... AO50: =(AO18+AO19)/(AN18+AN19)-1 -> 0.021054508 | AR50: Per share | AS50: =AS49/AO38 -> 496.42544
B51: Gross Margin | C51: =C23/C18 -> 0.21608833 | D51: =D23/D18 -> 0.21808511 | G51: =G23/G18 -> 0.21090047 | H51: =H23/H18 -> 0.22443182 | I51: =I23/I18 -> 0.22332155 | J51: =J23/J18 -> 0.27789746 | K51: =K23/K18 -> 0.22157007 | L51: =L23/L18 -> 0.22845691 | M51: =M23/M18 -> 0.2440273 | N51: =N23/N18 -> 0.31912397 | ... V51: =V23/V18 -> 0.34 | Z51: =Z23/Z18 -> 0.2253469 | AA51: =AA23/AA18 -> 0.24527302 | AB51: =AB23/AB18 -> 0.24087363 | AC51: =AC23/AC18 -> 0.26327526 | AD51: =AD23/AD18 -> 0.27545893 | AE51: =AE23/AE18 -> 0.2807211 | AF51: =AF23/AF18 -> 0.25 | AG51: =AG23/AG18 -> 0.25 | ... AO51: =AO23/AO18 -> 0.25 | AR51: Current price | AS51: =Main!D3 -> 1744.5
B52: Materials Margin | C52: =C20/C18 -> 0.52444795 | D52: =D20/D18 -> 0.4825228 | G52: =G20/G18 -> 0.54028436 | H52: =H20/H18 -> 0.50710227 | I52: =I20/I18 -> 0.56325088 | J52: =J20/J18 -> 0.42567859 | K52: =K20/K18 -> 0.65517241 | L52: =L20/L18 -> 0.5751503 | M52: =M20/M18 -> 0.57281001 | N52: =N20/N18 -> 0.4591318 | ... V52: =V20/V18 -> 0 | Z52: =Z20/Z18 -> 0.51655874 | AA52: =AA20/AA18 -> 0.48506803 | AB52: =AB20/AB18 -> 0.49656786 | AC52: =AC20/AC18 -> 0.54843206 | AD52: =AD20/AD18 -> 0.49830787 | AF52: =AF20/AF18 -> 0.5 | AG52: =AG20/AG18 -> 0.5 | AH52: =AH20/AH18 -> 0.5 | AI52: =AI20/AI18 -> 0.5 | AJ52: =AJ20/AJ18 -> 0.5 | AK52: =AK20/AK18 -> 0.5 | AL52: =AL20/AL18 -> 0.5 | AM52: =AM20/AM18 -> 0.5 | ... AO52: =AO20/AO18 -> 0.5 | AR52: Variance | AS52: =AS50/AS51-1 -> -0.71543397
B53: Personnel Margin | C53: =C21/C18 -> 0.32649842 | D53: =D21/D18 -> 0.32142857 | G53: =G21/G18 -> 0.36097946 | H53: =H21/H18 -> 0.32954545 | I53: =I21/I18 -> 0.31095406 | J53: =J21/J18 -> 0.20465317 | K53: =K21/K18 -> 0.36683786 | L53: =L21/L18 -> 0.33867735 | M53: =M21/M18 -> 0.28156997 | N53: =N21/N18 -> 0.2131404 | ... V53: =V21/V18 -> 0 | Z53: =Z21/Z18 -> 0.28436633 | AA53: =AA21/AA18 -> 0.29033398 | AB53: =AB21/AB18 -> 0.28642746 | AC53: =AC21/AC18 -> 0.28529617 | AD53: =AD21/AD18 -> 0.24335966 | AF53: =AF21/AF18 -> 0.25 | AG53: =AG21/AG18 -> 0.25 | AH53: =AH21/AH18 -> 0.25 | AI53: =AI21/AI18 -> 0.25 | AJ53: =AJ21/AJ18 -> 0.25 | AK53: =AK21/AK18 -> 0.25 | AL53: =AL21/AL18 -> 0.25 | AM53: =AM21/AM18 -> 0.25 | ... AO53: =AO21/AO18 -> 0.25 | AR53: Consensus | AS53: Heavily overvalued
B54: Other operating income y/y | G54: =G25/C25-1 -> 0.38095238 | H54: =H25/D25-1 -> 0.3 | I54: =I25/E25-1 -> #DIV/0! | J54: =J25/F25-1 -> #DIV/0! | K54: =K25/G25-1 -> 0.10344828 | L54: =L25/H25-1 -> -0.43589744 | M54: =M25/I25-1 -> -0.22641509 | N54: =N25/J25-1 -> -0.42 | ... V54: =V25/R25-1 -> 0.3 | AA54: =AA25/Z25-1 -> 0.1754386 | AB54: =AB25/AA25-1 -> 0.64925373 | AC54: =AC25/AB25-1 -> -0.30769231 | AD54: =AD25/AC25-1 -> 0.49019608 | AE54: =AE25/AD25-1 -> -1 | AF54: =AF25/AE25-1 -> #DIV/0! | AG54: =AG25/AF25-1 -> #DIV/0! | AH54: =AH25/AG25-1 -> #DIV/0! | ... AO54: =AO25/AN25-1 -> #DIV/0!
B55: Other operating expenses y/y | G55: =G26/C26-1 -> 0.026845638 | H55: =H26/D26-1 -> 0.077922078 | K55: =K26/G26-1 -> 0.18954248 | L55: =L26/H26-1 -> 0.10240964 | M55: =M26/I26-1 -> 0.12886598 | N55: =N26/J26-1 -> 0.19607843 | O55: =O26/K26-1 -> 0.25274725 | P55: =P26/L26-1 -> 0.5136612 | Q55: =Q26/M26-1 -> 0.12785388 | R55: =R26/N26-1 -> 0.20655738 | ... V55: =V26/R26-1 -> 0.1 | AA55: =AA26/Z26-1 -> 0.021806854 | AB55: =AB26/AA26-1 -> 0.17073171 | AC55: =AC26/AB26-1 -> 0.15755208 | AD55: =AD26/AC26-1 -> 0.25984252 | AE55: =AE26/AD26-1 -> -1 | AF55: =AF26/AE26-1 -> #DIV/0! | AG55: =AG26/AF26-1 -> #DIV/0! | AH55: =AH26/AG26-1 -> #DIV/0! | ... AO55: =AO26/AN26-1 -> #DIV/0!
B56: Operating Margin | C56: =C28/C18 -> 0.069400631 | D56: =D28/D18 -> 0.079787234 | G56: =G28/G18 -> 0.065560821 | H56: =H28/H18 -> 0.090198864 | I56: =I28/I18 -> 0.079151943 | J56: =J28/J18 -> 0.18354158 | K56: =K28/K18 -> 0.065297139 | L56: =L28/L18 -> 0.078824315 | M56: =M28/M18 -> 0.097838453 | N56: =N28/N18 -> 0.18224482 | ... V56: =V28/V18 -> 0.24569813 | Z56: =Z28/Z18 -> 0.075485661 | AA56: =AA28/AA18 -> 0.10867644 | AB56: =AB28/AB18 -> 0.11669267 | AC56: =AC28/AC18 -> 0.11777003 | AD56: =AD28/AD18 -> 0.14265204 | AE56: =AE28/AE18 -> 0.16228118 | AF56: =AF28/AF18 -> 0.14482962 | AG56: =AG28/AG18 -> 0.149524 | ... AO56: =AO28/AO18 -> 0.15337248
B57: Taxes | C57: =C35/C34 -> 0.27631579 | D57: =D35/D34 -> 0.23300971 | G57: =G35/G34 -> 0.20547945 | H57: =H35/H34 -> 0.30612245 | I57: =I35/I34 -> 0.27027027 | J57: =J35/J34 -> 0.24713959 | K57: =K35/K34 -> 0.28985507 | L57: =L35/L34 -> 0.29807692 | M57: =M35/M34 -> 0.24827586 | N57: =N35/N34 -> 0.19758065 | ... V57: =V35/V34 -> 0.27 | Z57: =Z35/Z34 -> 0.22677596 | AA57: =AA35/AA34 -> 0.25773196 | AB57: =AB35/AB34 -> 0.25452017 | AC57: =AC35/AC34 -> 0.22727273 | AD57: =AD35/AD34 -> 0.27117264 | AE57: =AE35/AE34 -> 0.26585352 | AF57: =AF35/AF34 -> 0.25 | AG57: =AG35/AG34 -> 0.25 | ... AO57: =AO35/AO34 -> 0.25
B58: MI | C58: =C36/C34 -> 0.065789474 | D58: =D36/D34 -> 1.1262136 | G58: =G36/G34 -> 0.16438356 | H58: =H36/H34 -> 0.1122449 | I58: =I36/I34 -> 0.045045045 | J58: =J36/J34 -> 0.073226545 | K58: =K36/K34 -> 0.014492754 | L58: =L36/L34 -> 0.15384615 | M58: =M36/M34 -> 0.048275862 | N58: =N36/N34 -> 0.14314516 | ... V58: =V36/V34 -> 0.1 | Z58: =Z36/Z34 -> 0.84699454 | AA58: =AA36/AA34 -> 0.24226804 | AB58: =AB36/AB34 -> 0.083449235 | AC58: =AC36/AC34 -> 0.11670762 | AD58: =AD36/AD34 -> 0.14495114 | AE58: =AE36/AE34 -> 0.10766257 | AF58: =AF36/AF34 -> 0.1 | AG58: =AG36/AG34 -> 0.1 | ... AO58: =AO36/AO34 -> 0.1
B59: Net Margin | C59: =C37/C23 -> 0.18248175 | D59: =D37/D23 -> -0.12891986 | G59: =G37/G23 -> 0.17228464 | H59: =H37/H23 -> 0.18037975 | I59: =I37/I23 -> 0.24050633 | J59: =J37/J23 -> 0.46046512 | K59: =K37/K23 -> 0.1589404 | L59: =L37/L23 -> 0.16666667 | M59: =M37/M23 -> 0.23776224 | N59: =N37/N23 -> 0.40073529 | ... V59: =V37/V23 -> 0.43065201 | Z59: =Z37/Z18 -> -0.0049953747 | AA59: =AA37/AA18 -> 0.051422513 | AB59: =AB37/AB18 -> 0.07425897 | AC59: =AC37/AC18 -> 0.074425087 | AD59: =AD37/AD18 -> 0.07353092 | AE59: =AE37/AE18 -> 0.094245195 | AF59: =AF37/AF18 -> 0.087432233 | AG59: =AG37/AG18 -> 0.090844564 | ... AO59: =AO37/AO18 -> 0.093157794
B61: L+S/E | T61: 14593
B63: EV/B | T63: =Main!D9/Model!T61 -> 5.2608703
B64: B/EV | T64: =T61/Main!D9-1 -> -0.80991738
B67: Model net profit | O67: =O37 -> 50 | P67: =P37 -> 63 | Q67: =Q37 -> 135 | R67: =R37 -> 469 | S67: =S37 -> 83 | T67: =T37 -> 143 | U67: =U37 -> 290.19816 | V67: =V37 -> 636.60341 | Z67: =Z37 -> -27 | AA67: =AA37 -> 291 | AB67: =AB37 -> 476 | AC67: =AC37 -> 534 | AD67: =AD37 -> 717 | AE67: =AE37 -> 1152.8016 | AF67: =AF37 -> 1264.6224 | AG67: =AG37 -> 1430.3841 | ... AO67: =AO37 -> 1804.5665
B68: CF net profit | O68: 54 | P68: =133-O68 -> 79 | Q68: =306-P68-O68 -> 173 | R68: =AD68-Q68-P68-O68 -> 502 | S68: 108 | T68: =267-S68 -> 159 | U68: =U67 -> 290.19816 | V68: =V67 -> 636.60341 | Y68: 354 | Z68: 1 | AA68: 332 | AB68: 535 | AC68: 586 | AD68: 808 | AE68: =AE67*1.1 -> 1268.0817 | AF68: =AF67*1.1 -> 1391.0847 | AG68: =AG67*1.1 -> 1573.4226 | AH68: =AH67*1.1 -> 1680.3052 | AI68: =AI67*1.1 -> 1747.2579 | AJ68: =AJ67*1.1 -> 1788.8858 | AK68: =AK67*1.1 -> 1826.287 | AL68: =AL67*1.1 -> 1864.5772 | ... AO68: =AO67*1.1 -> 1985.0231
B69: D&A | O69: 91 | P69: =181-O69 -> 90 | Q69: =277-P69-O69 -> 96 | R69: =AD69-Q69-P69-O69 -> 126 | S69: 112 | T69: =239-S69 -> 127 | U69: =Q69*1.4 -> 134.4 | V69: =R69*1.4 -> 176.4 | Y69: 280 | Z69: 557 | AA69: 254 | AB69: 249 | AC69: 308 | AD69: 403 | AE69: =SUM(S69:V69) -> 549.8 | AF69: =AE69*1.15 -> 632.27 | AG69: =AF69*1.1 -> 695.497 | AH69: =AG69*1.05 -> 730.27185 | AI69: =AH69*1.04 -> 759.48272 | AJ69: =AI69*1.03 -> 782.26721 | AK69: =AJ69*1.02 -> 797.91255 | AL69: =AK69*1.02 -> 813.8708 | AM69: =AL69*1.02 -> 830.14822 | AN69: =AM69*1.02 -> 846.75118 | AO69: =AN69*1.02 -> 863.6862
B70: Impairment | AA70: 91 | AB70: 12 | AC70: 63 | AD70: 0 | AE70: =SUM(S70:V70) -> 0 | AF70: 0 | AG70: 0 | AH70: 0 | AI70: 0 | AJ70: 0 | AK70: 0 | AL70: 0 | AM70: 0 | AN70: 0 | AO70: 0
B71: Pensions | O71: =-3-6 -> -9 | P71: =-7-O71 -> 2 | Q71: =-13-5-P71-O71 -> -11 | R71: =AD71-Q71-P71-O71 -> -6 | S71: =-4-3 -> -7 | T71: =14-S71 -> 21 | U71: -10 | V71: -25 | Y71: =-20-2 -> -22 | Z71: =-42-4 -> -46 | AA71: =-35-17 -> -52 | AB71: =-62-18 -> -80 | AC71: =-20+8 -> -12 | AD71: =-18-6 -> -24 | AE71: =SUM(S71:V71) -> -21 | AF71: =AE71*1.1 -> -23.1 | AG71: =AF71*1.1 -> -25.41 | AH71: =AG71*1.1 -> -27.951 | AI71: =AH71*1.1 -> -30.7461 | AJ71: =AI71*1.1 -> -33.82071 | AK71: =AJ71*1.1 -> -37.202781 | AL71: =AK71*1.1 -> -40.923059 | AM71: =AL71*1.1 -> -45.015365 | ... AO71: =AN71*1.1 -> -54.468592
B72: Loss on disposal | O72: 1 | P72: =69-O72 -> 68 | Q72: =66-P72-O72 -> -3 | R72: =AD72-Q72-P72-O72 -> 37 | S72: 0 | T72: 0 | U72: 0 | V72: 0 | Y72: 0 | Z72: -6 | AA72: 0 | AB72: -5 | AC72: -48 | AD72: 103 | AE72: =SUM(S72:V72) -> 0 | AF72: 0 | AG72: 0 | AH72: 0 | AI72: 0 | AJ72: 0 | AK72: 0 | AL72: 0 | AM72: 0 | AN72: 0 | AO72: 0
B73: Provisions | O73: 93 | P73: =16-O73 -> -77 | Q73: =94-P73-O73 -> 78 | R73: =AD73-Q73-P73-O73 -> 41 | S73: 90 | T73: =-15-S73 -> -105 | U73: 0 | V73: 110 | Y73: 23 | Z73: 88 | AA73: -51 | AB73: -9 | AC73: -59 | AD73: 135 | AE73: =SUM(S73:V73) -> 95 | AF73: 0 | AG73: 0 | AH73: 0 | AI73: 0 | AJ73: 0 | AK73: 0 | AL73: 0 | AM73: 0 | AN73: 0 | AO73: 0
B74: Working capital | O74: -202 | P74: =-74-O74 -> 128 | Q74: =-151-P74-O74 -> -77 | R74: =AD74-Q74-P74-O74 -> 558 | S74: 122 | T74: =-669-S74 -> -791 | U74: 0 | V74: =R74*1.5 -> 837 | Y74: 31 | Z74: -119 | AA74: 22 | AB74: -507 | AC74: 29 | AD74: 407 | AE74: =SUM(S74:V74) -> 168 | AF74: 0 | AG74: 0 | AH74: 0 | AI74: 0 | AJ74: 0 | AK74: 0 | AL74: 0 | AM74: 0 | AN74: 0 | AO74: 0
B75: Other working capital | O75: -145 | P75: =-159-O75 -> -14 | Q75: =-174-P75-O75 -> -15 | R75: =AD75-Q75-P75-O75 -> 72 | S75: -5 | T75: =-100-S75 -> -95 | U75: 0 | V75: 0 | Y75: -68 | Z75: -28 | AA75: 63 | AB75: -39 | AC75: -217 | AD75: -102 | AE75: =SUM(S75:V75) -> -100 | AF75: 0 | AG75: 0 | AH75: 0 | AI75: 0 | AJ75: 0 | AK75: 0 | AL75: 0 | AM75: 0 | AN75: 0 | AO75: 0
B76: Gain on investment | AC76: 39 | AD76: 0 | AE76: =SUM(S76:V76) -> 0 | AF76: 0 | AG76: 0 | AH76: 0 | AI76: 0 | AJ76: 0 | AK76: 0 | AL76: 0 | AM76: 0 | AN76: 0 | AO76: 0
B77: Loss on equity | O77: 1 | P77: =4-O77 -> 3 | Q77: =16-P77-O77 -> 12 | R77: =AD77-Q77-P77-O77 -> -1 | S77: 4 | T77: =4-S77 -> 0 | U77: 0 | V77: 0 | Y77: -37 | Z77: -10 | AA77: -15 | AB77: -32 | AC77: -4 | AD77: 15 | AE77: =SUM(S77:V77) -> 4 | AF77: 0 | AG77: 0 | AH77: 0 | AI77: 0 | AJ77: 0 | AK77: 0 | AL77: 0 | AM77: 0 | AN77: 0 | AO77: 0
B78: Gain on equity | O78: 0 | P78: 0 | Q78: =9-P78-O78 -> 9 | R78: =AD78-Q78-P78-O78 -> 7 | S78: 6 | T78: =8-S78 -> 2 | U78: 3 | V78: 5 | Y78: 17 | Z78: 21 | AA78: 30 | AB78: 17 | AC78: 29 | AD78: 16 | AE78: =SUM(S78:V78) -> 16 | AF78: 0 | AG78: 0 | AH78: 0 | AI78: 0 | AJ78: 0 | AK78: 0 | AL78: 0 | AM78: 0 | AN78: 0 | AO78: 0
B79: Other non-cash | O79: 11 | P79: =29-O79 -> 18 | Q79: =67-P79-O79 -> 38 | R79: =AD79-Q79-P79-O79 -> -109 | S79: -10 | T79: =-25-S79 -> -15 | U79: 0 | V79: 0 | Y79: 24 | Z79: -5 | AA79: 16 | AB79: 33 | AC79: 28 | AD79: -42 | AE79: =SUM(S79:V79) -> -25 | AF79: 0 | AG79: 0 | AH79: 0 | AI79: 0 | AJ79: 0 | AK79: 0 | AL79: 0 | AM79: 0 | AN79: 0 | AO79: 0
B80: CFFO | O80: =O68+SUM(O69:O79) -> -105 | P80: =P68+SUM(P69:P79) -> 297 | Q80: =Q68+SUM(Q69:Q79) -> 300 | R80: =R68+SUM(R69:R79) -> 1227 | S80: =S68+SUM(S69:S79) -> 420 | T80: =T68+SUM(T69:T79) -> -697 | U80: =U68+SUM(U69:U79) -> 417.59816 | V80: =V68+SUM(V69:V79) -> 1740.0034 | Y80: =Y68+SUM(Y69:Y79) -> 602 | Z80: =Z68+SUM(Z69:Z79) -> 453 | AA80: =AA68+SUM(AA69:AA79) -> 690 | AB80: =AB68+SUM(AB69:AB79) -> 174 | AC80: =AC68+SUM(AC69:AC79) -> 742 | AD80: =AD68+SUM(AD69:AD79) -> 1719 | AE80: =AE68+SUM(AE69:AE79) -> 1954.8817 | AF80: =AF68+SUM(AF69:AF79) -> 2000.2547 | ... AO80: =AO68+SUM(AO69:AO79) -> 2794.2407
B81: CapEx | O81: 105 | P81: =232-O81 -> 127 | Q81: =416-P81-O81 -> 184 | R81: =AD81-Q81-P81-O81 -> 316 | S81: 153 | T81: =352-S81 -> 199 | U81: =Q81*1.45 -> 266.8 | V81: =R81*1.45 -> 458.2 | Y81: 288 | Z81: 237 | AA81: 271 | AB81: 349 | AC81: 398 | AD81: 732 | AE81: =SUM(S81:V81) -> 1077 | AF81: =AE81*1.1 -> 1184.7 | AG81: =AF81*0.9 -> 1066.23 | AH81: =AG81*0.9 -> 959.607 | AI81: =AH81*0.9 -> 863.6463 | AJ81: =AI81*0.9 -> 777.28167 | AK81: =AJ81*0.95 -> 738.41759 | AL81: =AK81*0.95 -> 701.49671 | AM81: =AL81*0.95 -> 666.42187 | AN81: =AM81*0.95 -> 633.10078 | AO81: =AN81*0.95 -> 601.44574
B82: FCF | O82: =O80-O81 -> -210 | P82: =P80-P81 -> 170 | Q82: =Q80-Q81 -> 116 | R82: =R80-R81 -> 911 | S82: =S80-S81 -> 267 | T82: =T80-T81 -> -896 | U82: =U80-U81 -> 150.79816 | V82: =V80-V81 -> 1281.8034 | Y82: =Y80-Y81 -> 314 | Z82: =Z80-Z81 -> 216 | AA82: =AA80-AA81 -> 419 | AB82: =AB80-AB81 -> -175 | AC82: =AC80-AC81 -> 344 | AD82: =AD80-AD81 -> 987 | AE82: =AE80-AE81 -> 877.88172 | AF82: =AF80-AF81 -> 815.55466 | ... AO82: =AO80-AO81 -> 2192.795 | AP82: =AO82*(1+AS45) -> 2170.867 | AQ82: =AP82*(1+AT45) -> 2170.867 | AR82: =AQ82*(1+AU45) -> 2170.867 | AS82: =AR82*(1+AV45) -> 2170.867 | AT82: =AS82*(1+AW45) -> 2170.867 | AU82: =AT82*(1+AX45) -> 2170.867 | AV82: =AU82*(1+AY45) -> 2170.867 | AW82: =AV82*(1+AZ45) -> 2170.867 | ... EI82: =EH82*(1+EL45) -> 2170.867
B84: CapEx y/y | S84: =S81/O81-1 -> 0.45714286 | T84: =T81/P81-1 -> 0.56692913 | U84: =U81/Q81-1 -> 0.45 | V84: =V81/R81-1 -> 0.45 | AS84: =NPV(AS46,AE82:EI82) -> 26107.61
AS85: =AS48 -> -293
AS86: =AS84+AS85 -> 25814.61
AS87: =AS86/AO38 -> 588.8369
AS88: =Main!D3 -> 1744.5
AS89: =AS87/AS88-1 -> -0.66246093
